CHANGELOG.md
LICENSE
MANIFEST.in
README.md
RELEASE.md
install.json
package.json
pyproject.toml
setup.py
tsconfig.json
yarn.lock
jupyter-config/nb-config/observacode.json
jupyter-config/server-config/observacode.json
observacode/__init__.py
observacode/_version.py
observacode/handlers.py
observacode.egg-info/PKG-INFO
observacode.egg-info/SOURCES.txt
observacode.egg-info/dependency_links.txt
observacode.egg-info/not-zip-safe
observacode.egg-info/requires.txt
observacode.egg-info/top_level.txt
observacode/labextension/build_log.json
observacode/labextension/package.json
observacode/labextension/schemas/observacode/clear.json
observacode/labextension/schemas/observacode/package.json.orig
observacode/labextension/schemas/observacode/save.json
observacode/labextension/static/lib_index_js-webpack_sharing_consume_default_emotion_react_emotion_react-webpack_sharing_cons-092fe4.059e0d90c2e63549e35a.js
observacode/labextension/static/lib_index_js-webpack_sharing_consume_default_emotion_react_emotion_react-webpack_sharing_cons-092fe4.059e0d90c2e63549e35a.js.map
observacode/labextension/static/lib_index_js-webpack_sharing_consume_default_emotion_react_emotion_react-webpack_sharing_cons-092fe4.163bad1636b6ee607515.js
observacode/labextension/static/lib_index_js-webpack_sharing_consume_default_emotion_react_emotion_react-webpack_sharing_cons-092fe4.163bad1636b6ee607515.js.map
observacode/labextension/static/lib_index_js-webpack_sharing_consume_default_emotion_react_emotion_react-webpack_sharing_cons-092fe4.407c28f95fd7a88adc01.js
observacode/labextension/static/lib_index_js-webpack_sharing_consume_default_emotion_react_emotion_react-webpack_sharing_cons-092fe4.407c28f95fd7a88adc01.js.map
observacode/labextension/static/lib_index_js-webpack_sharing_consume_default_emotion_react_emotion_react-webpack_sharing_cons-092fe4.422cdc102f232cd201e8.js
observacode/labextension/static/lib_index_js-webpack_sharing_consume_default_emotion_react_emotion_react-webpack_sharing_cons-092fe4.422cdc102f232cd201e8.js.map
observacode/labextension/static/lib_index_js-webpack_sharing_consume_default_emotion_react_emotion_react-webpack_sharing_cons-092fe4.44cd646fca43d6f48570.js
